sample_shared/__init__.py
cktgym_sample_shared-0.0.4.dist-info/METADATA
cktgym_sample_shared-0.0.4.dist-info/WHEEL
cktgym_sample_shared-0.0.4.dist-info/top_level.txt
cktgym_sample_shared-0.0.4.dist-info/RECORD
